sendspin_gui/__init__.py
sendspin_gui/__main__.py
sendspin_gui/app.py
sendspin_gui/components/__init__.py
sendspin_gui/components/clients_panel.py
sendspin_gui/components/event_log.py
sendspin_gui/components/groups_panel.py
sendspin_gui/components/server_panel.py
sendspin_gui/components/stream_panel.py
sendspin_gui/utils/__init__.py
sendspin_gui/utils/async_bridge.py
sendspin_gui/utils/audio_decoder.py
sendspin_gui/utils/audio_gen.py
sendspin_gui/utils/log_handler.py
sendspin_dev_server-0.1.0.dist-info/METADATA
sendspin_dev_server-0.1.0.dist-info/WHEEL
sendspin_dev_server-0.1.0.dist-info/entry_points.txt
sendspin_dev_server-0.1.0.dist-info/RECORD
