Metadata-Version: 2.4
Name: sendspin-dev-server
Version: 0.1.0
Summary: A GUI wrapper for testing and iterating on the aiosendspin server
Project-URL: Homepage, https://github.com/chrisuthe/Sendspin-dev-server
Project-URL: Repository, https://github.com/chrisuthe/Sendspin-dev-server
Project-URL: Issues, https://github.com/chrisuthe/Sendspin-dev-server/issues
Author: Chris Uthe
License-Expression: MIT
Keywords: audio,gui,sendspin,streaming,testing
Classifier: Development Status :: 3 - Alpha
Classifier: Intended Audience :: Developers
Classifier: License :: OSI Approved :: MIT License
Classifier: Programming Language :: Python :: 3
Classifier: Programming Language :: Python :: 3.12
Classifier: Programming Language :: Python :: 3.13
Classifier: Topic :: Multimedia :: Sound/Audio
Requires-Python: >=3.12
Requires-Dist: aiosendspin>=3.0.0
Requires-Dist: av>=12.0.0
Requires-Dist: customtkinter>=5.2.0
Requires-Dist: numpy>=1.24.0
Requires-Dist: pillow>=10.0.0
Provides-Extra: dev
Requires-Dist: pytest-asyncio>=0.21.0; extra == 'dev'
Requires-Dist: pytest>=7.0.0; extra == 'dev'
Requires-Dist: ruff>=0.1.0; extra == 'dev'
